pybass3/__init__.py
pybass3/bass_channel.py
pybass3/bass_module.py
pybass3/bass_stream.py
pybass3/bass_tags.py
pybass3/datatypes.py
pybass3/playlist.py
pybass3/pys2_playlist.py
pybass3/pys2_song.py
pybass3/qtd.py
pybass3/song.py
pybass3/codes/__init__.py
pybass3/codes/channel.py
pybass3/codes/config.py
pybass3/codes/errors.py
pybass3/codes/info.py
pybass3/codes/tag.py
pybass3/structs/__init__.py
pybass3/structs/id.py
pybass3/structs/info.py
pybass3/vendor/BASS_LICENSE.txt
pybass3/vendor/PYBASS_LICENSE.txt
pybass3/vendor/__init__.py
pybass3/vendor/bass.dll
pybass3/vendor/bass.h
pybass3/vendor/tags-readme.txt
pybass3/vendor/tags.dll
PyBASS3-0.2.0.dist-info/LICENSE.txt
PyBASS3-0.2.0.dist-info/METADATA
PyBASS3-0.2.0.dist-info/WHEEL
PyBASS3-0.2.0.dist-info/top_level.txt
PyBASS3-0.2.0.dist-info/RECORD
