Metadata-Version: 2.1
Name: PyBASS3
Version: 0.2.0
Summary: A managed ctypes wrapper around the BASS audio library
Home-page: https://github.com/devdave/pybass3
Author: DevDave (David Ward)
Author-email: devdave@ominian.net
License: UNKNOWN
Platform: UNKNOWN
Classifier: Programming Language :: Python :: 3
Classifier: Operating System :: Microsoft :: Windows
Classifier: Development Status :: 3 - Alpha
Classifier: Intended Audience :: Developers
Classifier: License :: Free for non-commercial use
Classifier: Natural Language :: English
Classifier: Topic :: Multimedia :: Sound/Audio
Requires-Python: >= 3.6
License-File: LICENSE.txt
